dcoded/__init__.py
dcoded/discord.py
dcoded/file.py
dcoded/request.py
tests/test.py
dcoded-9.dist-info/LICENSE
dcoded-9.dist-info/METADATA
dcoded-9.dist-info/WHEEL
dcoded-9.dist-info/top_level.txt
dcoded-9.dist-info/RECORD
