Metadata-Version: 2.1
Name: dcoded
Version: 9
Summary: dcoded - the Python package for everything
Author-email: Dylan Rogers <opendylan@proton.me>
Project-URL: Homepage, https://github.com/dylanopen/dcoded-python
Project-URL: Bug Tracker, https://github.com/dylanopen/dcoded-python/issues
Classifier: Programming Language :: Python
Classifier: License :: OSI Approved :: MIT License
Classifier: Operating System :: OS Independent
Requires-Python: >=2.0
License-File: LICENSE
